{
    "$schema": "https://turborepo.com/schema.json",
    "tasks": {
        "build": {
            "dependsOn": ["lint", "check-env", "insert-superadmin", "^build"],
            "outputs": ["./.next/**", "!./.next/cache/**", "./dist/**", "./build/**"],
            "inputs": ["$TURBO_DEFAULT$", "../../.env*"]
        },
        "start": {
            "dependsOn": ["build"],
            "persistent": true,
            "cache": false
        },
        "check-types": {
            "dependsOn": ["prisma:generate", "^check-types"]
        },
        "lint": {
            "dependsOn": ["^lint"]
        },
        "format": {
            "dependsOn": ["^format"]
        },
        "dev": {
            "dependsOn": ["check-env", "insert-superadmin", "^dev"],
            "persistent": true,
            "cache": false
        },
        "prisma:generate": {
            "dependsOn": ["^prisma:generate"],
            "outputs": ["./src/generated/prisma/**"]
        },
        "check-env": {
            "dependsOn": ["^check-env"],
            "inputs": ["$TURBO_DEFAULT$", "../../.env*"]
        },
        "insert-superadmin": {
            "dependsOn": ["check-env", "prisma:generate", "^insert-superadmin"]
        }
    }
}
